solvers/__init__.py
solvers/common/__init__.py
solvers/common/cell.py
solvers/common/expr.py
solvers/common/grid.py
solvers/common/less_than_op.py
solvers/common/neighbourhood.py
solvers/common/region.py
solvers/common/sum_region.py
solvers/constraints/column_all_different.py
solvers/constraints/predefined_values.py
solvers/constraints/puzzle_constraint.py
solvers/constraints/row_all_different.py
solvers/constraints/solution_converter.py
solvers/constraints/solver_status.py
solvers/doplo/__init__.py
solvers/doplo/doplo_solver.py
solvers/futoshiki/__init__.py
solvers/futoshiki/futoshiki_solver.py
solvers/killer_sudoku/__init__.py
solvers/killer_sudoku/killer_sudoku_solver.py
solvers/samurai_sudoku/__init__.py
solvers/samurai_sudoku/samurai_sudoku_solver.py
solvers/sudoku/__init__.py
solvers/sudoku/sudoku_solver.py
solvers/suguru/__init__.py
solvers/suguru/suguru_solver.py
solvers/yakuso/__init__.py
solvers/yakuso/yakuso_solver.py
solvers/zehnergitter/__init__.py
solvers/zehnergitter/zehnergitter_solver.py
ortools_puzzles_solvers-1.0.0.dist-info/WHEEL
ortools_puzzles_solvers-1.0.0.dist-info/METADATA
ortools_puzzles_solvers-1.0.0.dist-info/licenses/LICENSE
ortools_puzzles_solvers-1.0.0.dist-info/RECORD
