Metadata-Version: 2.1
Name: ortools-puzzles-solvers
Version: 1.0.0
Summary: Constraint Solvers for common puzzles using OR-Tools.
Author-email: Andrin Meier <andrin@pricemeier.ch>
Requires-Python: >=3.8
Requires-Dist: ortools>=9.3.10497
Project-URL: Homepage, https://github.com/andrinmeier/solvers
